sigma/backends/netwitness/__init__.py
sigma/backends/netwitness/netwitness.py
sigma/backends/netwitness/transformations.py
sigma/backends/netwitness/types.py
sigma/pipelines/netwitness/__init__.py
sigma/pipelines/netwitness/netwitness.py
sigma/pipelines/netwitness/schemas.py
sigma/pipelines/netwitness/windows.py
pysigma_backend_netwitness-0.2.5.dist-info/LICENSE
pysigma_backend_netwitness-0.2.5.dist-info/METADATA
pysigma_backend_netwitness-0.2.5.dist-info/WHEEL
pysigma_backend_netwitness-0.2.5.dist-info/RECORD
