Metadata-Version: 2.3
Name: pySigma-backend-netwitness
Version: 0.2.5
Summary: pySigma NetWitness backend
License: LGPL-2.1-only
Author: Marcel Kwaschny
Author-email: dev@marcelkwaschny.de
Requires-Python: >=3.9,<4.0
Classifier: License :: OSI Approved
Classifier: Programming Language :: Python :: 3
Classifier: Programming Language :: Python :: 3.9
Classifier: Programming Language :: Python :: 3.10
Classifier: Programming Language :: Python :: 3.11
Classifier: Programming Language :: Python :: 3.12
Classifier: Programming Language :: Python :: 3.13
Requires-Dist: pysigma (>=0.11.0)
Project-URL: Repository, https://github.com/marcelkwaschny/pySigma-backend-netwitness
